_version.py
battle_map_tv/__init__.py
battle_map_tv/__main__.py
battle_map_tv/events.py
battle_map_tv/grid.py
battle_map_tv/image.py
battle_map_tv/initiative.py
battle_map_tv/scale_detection.py
battle_map_tv/storage.py
battle_map_tv/utils.py
battle_map_tv/window_gui.py
battle_map_tv/window_image.py
battle_map_tv-0.9.0.dist-info/METADATA
battle_map_tv-0.9.0.dist-info/WHEEL
battle_map_tv-0.9.0.dist-info/licenses/LICENSE
battle_map_tv-0.9.0.dist-info/RECORD
