Metadata-Version: 2.4
Name: battle_map_tv
Version: 0.9.0
Summary: Display battle maps for TTRPGs on a secondary tv
Project-URL: Homepage, https://github.com/Conengmo/battle-map-tv
Project-URL: Issues, https://github.com/Conengmo/battle-map-tv/issues
Author-email: Frank <33519926+Conengmo@users.noreply.github.com>
License-File: LICENSE
Classifier: License :: OSI Approved :: GNU General Public License v3 (GPLv3)
Classifier: Operating System :: OS Independent
Classifier: Programming Language :: Python :: 3
Requires-Python: >=3.8
Requires-Dist: numpy
Requires-Dist: opencv-python
Requires-Dist: platformdirs
Requires-Dist: pyside6!=6.6.3.*
